{
    "PPoPP_17_001": {
        "citedby": {
            "2017-05-04": 0,
            "2017-06-04": 0,
            "2017-07-04": 0,
            "2017-08-04": 0,
            "2017-09-04": 1,
            "2017-10-04": 1,
            "2017-11-04": 1,
            "2017-12-04": 1,
            "2018-01-04": 1,
            "2018-02-04": 1,
            "2018-03-04": 5,
            "2018-04-04": 5,
            "2018-05-04": 5,
            "2018-06-04": 5,
            "2018-08-04": 6,
            "2018-11-04": 7,
            "2019-02-04": 8,
            "2019-08-15": 10,
            "2020-02-04": 15,
            "2020-08-04": 22,
            "2021-02-04": 24
        },
        "eprint_found": "2017-05-04",
        "id": "yeh2017pagoda",
        "paper_found": "2017-05-04",
        "title": "Pagoda: Fine-grained GPU resource virtualization for narrow tasks",
        "url": "https://engineering.purdue.edu/tgrogers/papers/tsung.tai.ppopp.2017.pdf"
    },
    "PPoPP_17_002": {
        "citedby": {
            "2017-05-04": 1,
            "2017-06-04": 1,
            "2017-07-04": 1,
            "2017-08-04": 1,
            "2017-09-04": 1,
            "2017-10-04": 3,
            "2017-11-04": 3,
            "2017-12-04": 5,
            "2018-01-04": 6,
            "2018-02-04": 8,
            "2018-03-04": 9,
            "2018-04-04": 9,
            "2018-05-04": 9,
            "2018-06-04": 10,
            "2018-08-04": 11,
            "2018-11-04": 13,
            "2019-02-04": 16,
            "2019-08-15": 24,
            "2020-02-04": 39,
            "2020-08-04": 50,
            "2021-02-04": 66
        },
        "eprint_found": "2017-05-04",
        "id": "schardl2017tapir",
        "paper_found": "2017-05-04",
        "title": "Tapir: Embedding fork-join parallelism into LLVM's intermediate representation",
        "url": "https://dl.acm.org/doi/pdf/10.1145/3155284.3018758"
    },
    "PPoPP_17_003": {
        "citedby": {
            "2017-05-04": 0,
            "2017-06-04": 0,
            "2017-07-04": 1,
            "2017-08-04": 1,
            "2017-09-04": 1,
            "2017-10-04": 1,
            "2017-11-04": 2,
            "2017-12-04": 6,
            "2018-01-04": 8,
            "2018-02-04": 8,
            "2018-03-04": 9,
            "2018-04-04": 9,
            "2018-05-04": 9,
            "2018-06-04": 9,
            "2018-08-04": 14,
            "2018-11-04": 18,
            "2019-02-04": 19,
            "2019-08-15": 34,
            "2020-02-04": 47,
            "2020-08-04": 58,
            "2021-02-04": 78
        },
        "eprint_found": "2017-05-04",
        "id": "ben2017groute",
        "paper_found": "2017-05-04",
        "title": "Groute: An asynchronous multi-GPU programming model for irregular computations",
        "url": "https://dl.acm.org/doi/pdf/10.1145/3155284.3018756"
    },
    "PPoPP_17_004": {
        "citedby": {
            "2017-05-04": 0,
            "2017-06-04": 2,
            "2017-07-04": 2,
            "2017-08-04": 2,
            "2017-09-04": 2,
            "2017-10-04": 2,
            "2017-11-04": 2,
            "2017-12-04": 2,
            "2018-01-04": 2,
            "2018-02-04": 2,
            "2018-03-04": 2,
            "2018-04-04": 2,
            "2018-05-04": 2,
            "2018-06-04": 2,
            "2018-08-04": 3,
            "2018-11-04": 3,
            "2019-02-04": 6,
            "2019-08-15": 6,
            "2020-02-04": 6,
            "2020-08-04": 7,
            "2021-02-04": 10
        },
        "eprint_found": "2017-06-04",
        "id": "tang2017self",
        "paper_found": "2017-05-04",
        "title": "Self-checkpoint: An in-memory checkpoint method using less space and its practice on fault-tolerant HPL",
        "url": "http://pacman.cs.tsinghua.edu.cn/~cwg/papers_cwg/ppopp17.pdf"
    },
    "PPoPP_17_005": {
        "citedby": {
            "2017-05-04": 0,
            "2017-06-04": 0,
            "2017-07-04": 0,
            "2017-08-04": 0,
            "2017-09-04": 1,
            "2017-10-04": 2,
            "2017-11-04": 3,
            "2017-12-04": 3,
            "2018-01-04": 3,
            "2018-02-04": 3,
            "2018-03-04": 3,
            "2018-04-04": 3,
            "2018-05-04": 4,
            "2018-06-04": 5,
            "2018-08-04": 5,
            "2018-11-04": 5,
            "2019-02-04": 5,
            "2019-08-15": 6,
            "2020-02-04": 6,
            "2020-08-04": 6,
            "2021-02-04": 7
        },
        "eprint_found": "2017-05-04",
        "id": "vollmer2017sc",
        "paper_found": "2017-05-04",
        "title": "Sc-haskell: Sequential consistency in languages that minimize mutable shared heap",
        "url": "https://dl.acm.org/doi/pdf/10.1145/3155284.3018746"
    },
    "PPoPP_17_006": {
        "citedby": {
            "2017-05-04": 0,
            "2017-06-04": 0,
            "2017-07-04": 0,
            "2017-08-04": 0,
            "2017-09-04": 0,
            "2017-10-04": 0,
            "2017-11-04": 0,
            "2017-12-04": 0,
            "2018-01-04": 0,
            "2018-02-04": 0,
            "2018-03-04": 1,
            "2018-04-04": 1,
            "2018-05-04": 1,
            "2018-06-04": 1,
            "2018-08-04": 2,
            "2018-11-04": 3,
            "2019-02-04": 4,
            "2019-08-15": 5,
            "2020-02-04": 7,
            "2020-08-04": 7,
            "2021-02-04": 8
        },
        "eprint_found": "",
        "id": "battig2017synchronized",
        "paper_found": "2017-05-04",
        "title": "Synchronized-by-default concurrency for shared-memory systems",
        "url": ""
    },
    "PPoPP_17_007": {
        "citedby": {
            "2017-05-04": 0,
            "2017-06-04": 0,
            "2017-07-04": 0,
            "2017-08-04": 1,
            "2017-09-04": 1,
            "2017-10-04": 1,
            "2017-11-04": 1,
            "2017-12-04": 2,
            "2018-01-04": 2,
            "2018-02-04": 2,
            "2018-03-04": 2,
            "2018-04-04": 2,
            "2018-05-04": 2,
            "2018-06-04": 2,
            "2018-08-04": 2,
            "2018-11-04": 3,
            "2019-02-04": 5,
            "2019-08-15": 9,
            "2020-02-04": 10,
            "2020-08-04": 14,
            "2021-02-04": 19
        },
        "eprint_found": "2017-05-04",
        "id": "ou2017checking",
        "paper_found": "2017-05-04",
        "title": "Checking concurrent data structures under the C/C++ 11 memory model",
        "url": "https://dl.acm.org/doi/pdf/10.1145/3155284.3018749"
    },
    "PPoPP_17_008": {
        "citedby": {
            "2017-05-04": 0,
            "2017-06-04": 0,
            "2017-07-04": 0,
            "2017-08-04": 0,
            "2017-09-04": 0,
            "2017-10-04": 0,
            "2017-11-04": 0,
            "2017-12-04": 0,
            "2018-01-04": 0,
            "2018-02-04": 0,
            "2018-03-04": 1,
            "2018-04-04": 2,
            "2018-05-04": 2,
            "2018-06-04": 2,
            "2018-08-04": 3,
            "2018-11-04": 3,
            "2019-02-04": 4,
            "2019-08-15": 5,
            "2020-02-04": 6,
            "2020-08-04": 9,
            "2021-02-04": 10
        },
        "eprint_found": "2017-05-04",
        "id": "chabbi2017efficient",
        "paper_found": "2017-05-04",
        "title": "An efficient abortable-locking protocol for multi-level NUMA systems",
        "url": "https://www.mcs.anl.gov/~aamer/papers/ppopp17_hmcst.pdf"
    },
    "PPoPP_17_009": {
        "citedby": {
            "2017-05-04": 0,
            "2017-06-04": 0,
            "2017-07-04": 0,
            "2017-08-04": 0,
            "2017-09-04": 0,
            "2017-10-04": 0,
            "2017-11-04": 0,
            "2017-12-04": 0,
            "2018-01-04": 2,
            "2018-02-04": 2,
            "2018-03-04": 2,
            "2018-04-04": 2,
            "2018-05-04": 2,
            "2018-06-04": 3,
            "2018-08-04": 4,
            "2018-11-04": 6,
            "2019-02-04": 7,
            "2019-08-15": 11,
            "2020-02-04": 13,
            "2020-08-04": 17,
            "2021-02-04": 22
        },
        "eprint_found": "2018-01-04",
        "id": "wu2017silent",
        "paper_found": "2017-05-04",
        "title": "Silent data corruption resilient two-sided matrix factorizations",
        "url": "https://dl.acm.org/doi/pdf/10.1145/3155284.3018750"
    },
    "PPoPP_17_010": {
        "citedby": {
            "2017-05-04": 0,
            "2017-06-04": 0,
            "2017-07-04": 1,
            "2017-08-04": 1,
            "2017-09-04": 1,
            "2017-10-04": 1,
            "2017-11-04": 1,
            "2017-12-04": 1,
            "2018-01-04": 1,
            "2018-02-04": 1,
            "2018-03-04": 1,
            "2018-04-04": 1,
            "2018-05-04": 1,
            "2018-06-04": 1,
            "2018-08-04": 1,
            "2018-11-04": 3,
            "2019-02-04": 3,
            "2019-08-15": 2,
            "2020-02-04": 3,
            "2020-08-04": 3,
            "2021-02-04": 3
        },
        "eprint_found": "2017-05-04",
        "id": "moreira2017function",
        "paper_found": "2017-05-04",
        "title": "Function call re-vectorization",
        "url": "https://repositorio.ufmg.br/bitstream/1843/ESBF-ANJQK8/1/rubensemilio.pdf"
    },
    "PPoPP_17_011": {
        "citedby": {
            "2017-05-04": 0,
            "2017-06-04": 0,
            "2017-07-04": 0,
            "2017-08-04": 0,
            "2017-09-04": 0,
            "2017-10-04": 0,
            "2017-11-04": 1,
            "2017-12-04": 2,
            "2018-01-04": 2,
            "2018-02-04": 2,
            "2018-03-04": 4,
            "2018-04-04": 4,
            "2018-05-04": 5,
            "2018-06-04": 5,
            "2018-08-04": 6,
            "2018-11-04": 7,
            "2019-02-04": 7,
            "2019-08-15": 9,
            "2020-02-04": 11,
            "2020-08-04": 13,
            "2021-02-04": 20
        },
        "eprint_found": "2017-05-04",
        "id": "wang2017eunomia",
        "paper_found": "2017-05-04",
        "title": "Eunomia: Scaling concurrent search trees under contention using htm",
        "url": "http://news.cs.nyu.edu/~zhaoguo/pub/eunomia-ppopp17.pdf"
    },
    "PPoPP_17_012": {
        "citedby": {
            "2017-05-04": 0,
            "2017-06-04": 0,
            "2017-07-04": 0,
            "2017-08-04": 0,
            "2017-09-04": 0,
            "2017-10-04": 0,
            "2017-11-04": 0,
            "2017-12-04": 0,
            "2018-01-04": 0,
            "2018-02-04": 0,
            "2018-03-04": 0,
            "2018-04-04": 0,
            "2018-05-04": 0,
            "2018-06-04": 0,
            "2018-08-04": 1,
            "2018-11-04": 4,
            "2019-02-04": 4,
            "2019-08-15": 5,
            "2020-02-04": 6,
            "2020-08-04": 6,
            "2021-02-04": 7
        },
        "eprint_found": "2017-12-04",
        "id": "cohen2017layout",
        "paper_found": "2017-05-04",
        "title": "Layout Lock: A Scalable Locking Paradigm for Concurrent Data Layout Modifications",
        "url": "http://www.cs.technion.ac.il/~erez/Papers/ctp-ppopp17.pdf"
    },
    "PPoPP_17_013": {
        "citedby": {
            "2017-05-04": 0,
            "2017-06-04": 0,
            "2017-07-04": 2,
            "2017-08-04": 2,
            "2017-09-04": 3,
            "2017-10-04": 3,
            "2017-11-04": 3,
            "2017-12-04": 3,
            "2018-01-04": 3,
            "2018-02-04": 2,
            "2018-03-04": 2,
            "2018-04-04": 2,
            "2018-05-04": 3,
            "2018-06-04": 3,
            "2018-08-04": 6,
            "2018-11-04": 7,
            "2019-02-04": 7,
            "2019-08-15": 15,
            "2020-02-04": 21,
            "2020-08-04": 28,
            "2021-02-04": 36
        },
        "eprint_found": "2017-05-04",
        "id": "zhang2017understanding",
        "paper_found": "2017-05-04",
        "title": "Understanding the gpu microarchitecture to achieve bare-metal performance tuning",
        "url": "https://www.researchgate.net/profile/Xiuxia_Zhang2/publication/313020335_Understanding_the_GPU_Microarchitecture_to_Achieve_Bare-Metal_Performance_Tuning/links/5adfb84da6fdcc29358fd8b5/Understanding-the-GPU-Microarchitecture-to-Achieve-Bare-Metal-Performance-Tuning.pdf"
    },
    "PPoPP_17_014": {
        "citedby": {
            "2017-05-04": 2,
            "2017-06-04": 2,
            "2017-07-04": 3,
            "2017-08-04": 3,
            "2017-09-04": 3,
            "2017-10-04": 3,
            "2017-11-04": 3,
            "2017-12-04": 3,
            "2018-01-04": 4,
            "2018-02-04": 5,
            "2018-03-04": 5,
            "2018-04-04": 5,
            "2018-05-04": 6,
            "2018-06-04": 7,
            "2018-08-04": 10,
            "2018-11-04": 17,
            "2019-02-04": 23,
            "2019-08-15": 30,
            "2020-02-04": 41,
            "2020-08-04": 48,
            "2021-02-04": 57
        },
        "eprint_found": "2017-05-04",
        "id": "chen2017effisha",
        "paper_found": "2017-05-04",
        "title": "Effisha: A software framework for enabling effficient preemptive scheduling of gpu",
        "url": "https://dl.acm.org/doi/pdf/10.1145/3155284.3018748"
    },
    "PPoPP_17_015": {
        "citedby": {
            "2017-05-04": 0,
            "2017-06-04": 0,
            "2017-07-04": 1,
            "2017-08-04": 1,
            "2017-09-04": 1,
            "2017-10-04": 1,
            "2017-11-04": 1,
            "2017-12-04": 1,
            "2018-01-04": 2,
            "2018-02-04": 2,
            "2018-03-04": 4,
            "2018-04-04": 4,
            "2018-05-04": 4,
            "2018-06-04": 5,
            "2018-08-04": 5,
            "2018-11-04": 9,
            "2019-02-04": 10,
            "2019-08-15": 14,
            "2020-02-04": 18,
            "2020-08-04": 20,
            "2021-02-04": 20
        },
        "eprint_found": "2017-05-04",
        "id": "prajapati2017simple",
        "paper_found": "2017-05-04",
        "title": "Simple, accurate, analytical time modeling and optimal tile size selection for gpgpu stencils",
        "url": "https://pollylabs.org/publications/grosser-2017-Simple-Accurate-Analytical-Time-Modeling-and-Optimal-Tile-Size-Selection-for-GPGPU-Stencils.pdf"
    },
    "PPoPP_17_016": {
        "citedby": {
            "2017-05-04": 0,
            "2017-06-04": 0,
            "2017-07-04": 0,
            "2017-08-04": 0,
            "2017-09-04": 0,
            "2017-10-04": 0,
            "2017-11-04": 0,
            "2017-12-04": 0,
            "2018-01-04": 0,
            "2018-02-04": 0,
            "2018-03-04": 0,
            "2018-04-04": 0,
            "2018-05-04": 0,
            "2018-06-04": 0,
            "2018-08-04": 0,
            "2018-11-04": 1,
            "2019-02-04": 1,
            "2019-08-15": 1,
            "2020-02-04": 3,
            "2020-08-04": 3,
            "2021-02-04": 3
        },
        "eprint_found": "2017-05-04",
        "id": "steele2017using",
        "paper_found": "2017-05-04",
        "title": "Using butterfly-patterned partial sums to draw from discrete distributions",
        "url": "https://on-demand.gputechconf.com/gtc/2016/presentation/s6666-guy-steele-butterfly-pattern.pdf"
    },
    "PPoPP_17_017": {
        "citedby": {
            "2017-05-04": 0,
            "2017-06-04": 1,
            "2017-07-04": 1,
            "2017-08-04": 1,
            "2017-09-04": 1,
            "2017-10-04": 1,
            "2017-11-04": 3,
            "2017-12-04": 3,
            "2018-01-04": 3,
            "2018-02-04": 3,
            "2018-03-04": 3,
            "2018-04-04": 3,
            "2018-05-04": 3,
            "2018-06-04": 3,
            "2018-08-04": 5,
            "2018-11-04": 5,
            "2019-02-04": 6,
            "2019-08-15": 11,
            "2020-02-04": 12,
            "2020-08-04": 13,
            "2021-02-04": 13
        },
        "eprint_found": "2017-05-04",
        "id": "ren2017exploiting",
        "paper_found": "2017-05-04",
        "title": "Exploiting vector and multicore parallelism for recursive, data-and task-parallel programs",
        "url": "https://dl.acm.org/doi/pdf/10.1145/3155284.3018763"
    },
    "PPoPP_17_018": {
        "citedby": {
            "2017-05-04": 0,
            "2017-06-04": 0,
            "2017-07-04": 0,
            "2017-08-04": 1,
            "2017-09-04": 1,
            "2017-10-04": 1,
            "2017-11-04": 2,
            "2017-12-04": 1,
            "2018-01-04": 3,
            "2018-02-04": 3,
            "2018-03-04": 3,
            "2018-04-04": 3,
            "2018-05-04": 3,
            "2018-06-04": 4,
            "2018-08-04": 5,
            "2018-11-04": 6,
            "2019-02-04": 7,
            "2019-08-15": 12,
            "2020-02-04": 15,
            "2020-08-04": 15,
            "2021-02-04": 19
        },
        "eprint_found": "2018-02-04",
        "id": "luo2017thread",
        "paper_found": "2017-05-04",
        "title": "Thread data sharing in cache: Theory and measurement",
        "url": "https://dl.acm.org/doi/pdf/10.1145/3155284.3018759"
    },
    "PPoPP_17_019": {
        "citedby": {
            "2017-05-04": 0,
            "2017-06-04": 0,
            "2017-07-04": 0,
            "2017-08-04": 0,
            "2017-09-04": 0,
            "2017-10-04": 1,
            "2017-11-04": 2,
            "2017-12-04": 2,
            "2018-01-04": 2,
            "2018-02-04": 2,
            "2018-03-04": 2,
            "2018-04-04": 2,
            "2018-05-04": 3,
            "2018-06-04": 3,
            "2018-08-04": 3,
            "2018-11-04": 5,
            "2019-02-04": 5,
            "2019-08-15": 6,
            "2020-02-04": 10,
            "2020-08-04": 16,
            "2021-02-04": 18
        },
        "eprint_found": "2017-05-04",
        "id": "jiang2017combining",
        "paper_found": "2017-05-04",
        "title": "Combining SIMD and Many/Multi-core parallelism for finite state machines with enumerative speculation",
        "url": "https://dl.acm.org/doi/pdf/10.1145/3155284.3018760"
    },
    "PPoPP_17_020": {
        "citedby": {
            "2017-05-04": 0,
            "2017-06-04": 0,
            "2017-07-04": 0,
            "2017-08-04": 0,
            "2017-09-04": 0,
            "2017-10-04": 1,
            "2017-11-04": 1,
            "2017-12-04": 2,
            "2018-01-04": 2,
            "2018-02-04": 3,
            "2018-03-04": 5,
            "2018-04-04": 6,
            "2018-05-04": 7,
            "2018-06-04": 7,
            "2018-08-04": 7,
            "2018-11-04": 10,
            "2019-02-04": 10,
            "2019-08-15": 19,
            "2020-02-04": 25,
            "2020-08-04": 30,
            "2021-02-04": 33
        },
        "eprint_found": "2017-05-04",
        "id": "basin2017kiwi",
        "paper_found": "2017-05-04",
        "title": "Kiwi: A key-value map for scalable real-time analytics",
        "url": "http://webee.technion.ac.il/Sites/People/idish/ftp/kiwi.pdf"
    },
    "PPoPP_17_021": {
        "citedby": {
            "2017-05-04": 0,
            "2017-06-04": 1,
            "2017-07-04": 1,
            "2017-08-04": 1,
            "2017-09-04": 1,
            "2017-10-04": 1,
            "2017-11-04": 1,
            "2017-12-04": 1,
            "2018-01-04": 1,
            "2018-02-04": 1,
            "2018-03-04": 1,
            "2018-04-04": 1,
            "2018-05-04": 2,
            "2018-06-04": 2,
            "2018-08-04": 3,
            "2018-11-04": 6,
            "2019-02-04": 6,
            "2019-08-15": 8,
            "2020-02-04": 11,
            "2020-08-04": 12,
            "2021-02-04": 13
        },
        "eprint_found": "2017-05-04",
        "id": "sato2017noise",
        "paper_found": "2017-05-04",
        "title": "Noise injection techniques to expose subtle and unintended message races",
        "url": "https://kento.github.io/files/2017-02-06-PPoPP2017-conf-paper.pdf"
    },
    "PPoPP_17_022": {
        "citedby": {
            "2017-05-04": 0,
            "2017-06-04": 0,
            "2017-07-04": 0,
            "2017-08-04": 0,
            "2017-09-04": 0,
            "2017-10-04": 0,
            "2017-11-04": 0,
            "2017-12-04": 0,
            "2018-01-04": 0,
            "2018-02-04": 0,
            "2018-03-04": 0,
            "2018-04-04": 1,
            "2018-05-04": 1,
            "2018-06-04": 1,
            "2018-08-04": 1,
            "2018-11-04": 1,
            "2019-02-04": 1,
            "2019-08-15": 3,
            "2020-02-04": 5,
            "2020-08-04": 5,
            "2021-02-04": 5
        },
        "eprint_found": "2017-05-04",
        "id": "acar2017contention",
        "paper_found": "2017-05-04",
        "title": "Contention in structured concurrency: Provably efficient dynamic non-zero indicators for nested parallelism",
        "url": "https://hal.inria.fr/hal-01416531/document"
    },
    "PPoPP_17_023": {
        "citedby": {
            "2017-05-04": 0,
            "2017-06-04": 0,
            "2017-07-04": 0,
            "2017-08-04": 0,
            "2017-09-04": 0,
            "2017-10-04": 0,
            "2017-11-04": 1,
            "2017-12-04": 1,
            "2018-01-04": 1,
            "2018-02-04": 1,
            "2018-03-04": 1,
            "2018-04-04": 1,
            "2018-05-04": 3,
            "2018-06-04": 3,
            "2018-08-04": 4,
            "2018-11-04": 4,
            "2019-02-04": 4,
            "2019-08-15": 7,
            "2020-02-04": 8,
            "2020-08-04": 9,
            "2021-02-04": 9
        },
        "eprint_found": "2017-05-04",
        "id": "utterback2017processor",
        "paper_found": "2017-05-04",
        "title": "Processor-oblivious record and replay",
        "url": "https://dl.acm.org/doi/pdf/10.1145/3155284.3018764"
    },
    "PPoPP_17_024": {
        "citedby": {
            "2017-05-04": 0,
            "2017-06-04": 0,
            "2017-07-04": 0,
            "2017-08-04": 0,
            "2017-09-04": 0,
            "2017-10-04": 0,
            "2017-11-04": 2,
            "2017-12-04": 3,
            "2018-01-04": 5,
            "2018-02-04": 4,
            "2018-03-04": 4,
            "2018-04-04": 5,
            "2018-05-04": 5,
            "2018-06-04": 6,
            "2018-08-04": 7,
            "2018-11-04": 8,
            "2019-02-04": 9,
            "2019-08-15": 13,
            "2020-02-04": 22,
            "2020-08-04": 24,
            "2021-02-04": 28
        },
        "eprint_found": "2017-05-04",
        "id": "sabne2017model",
        "paper_found": "2017-05-04",
        "title": "Model-based iterative CT image reconstruction on GPUs",
        "url": "https://scholar.harvard.edu/files/xiao.wang2/files/mbir_gpu.pdf"
    },
    "PPoPP_17_025": {
        "citedby": {
            "2017-05-04": 3,
            "2017-06-04": 3,
            "2017-07-04": 4,
            "2017-08-04": 4,
            "2017-09-04": 4,
            "2017-10-04": 4,
            "2017-11-04": 4,
            "2017-12-04": 4,
            "2018-01-04": 4,
            "2018-02-04": 5,
            "2018-03-04": 6,
            "2018-04-04": 6,
            "2018-05-04": 6,
            "2018-06-04": 6,
            "2018-08-04": 6,
            "2018-11-04": 6,
            "2019-02-04": 7,
            "2019-08-15": 12,
            "2020-02-04": 16,
            "2020-08-04": 17,
            "2021-02-04": 18
        },
        "eprint_found": "2017-05-04",
        "id": "matveev2017multicore",
        "paper_found": "2017-05-04",
        "title": "A multicore path to connectomics-on-demand",
        "url": "https://dl.acm.org/doi/pdf/10.1145/3155284.3018766"
    },
    "PPoPP_17_026": {
        "citedby": {
            "2017-05-04": 0,
            "2017-06-04": 0,
            "2017-07-04": 0,
            "2017-08-04": 0,
            "2017-09-04": 0,
            "2017-10-04": 0,
            "2017-11-04": 0,
            "2017-12-04": 0,
            "2018-01-04": 0,
            "2018-02-04": 0,
            "2018-03-04": 0,
            "2018-04-04": 0,
            "2018-05-04": 0,
            "2018-06-04": 0,
            "2018-08-04": 0,
            "2018-11-04": 0,
            "2019-02-04": 0,
            "2019-08-15": 2,
            "2020-02-04": 3,
            "2020-08-04": 3,
            "2021-02-04": 3
        },
        "eprint_found": "2018-01-04",
        "id": "rajbhandari2017optimizing",
        "paper_found": "2017-05-04",
        "title": "Optimizing the four-index integral transform using data movement lower bounds analysis",
        "url": "https://dl.acm.org/doi/pdf/10.1145/3155284.3018771"
    },
    "PPoPP_17_027": {
        "citedby": {
            "2017-05-04": 0,
            "2017-06-04": 0,
            "2017-07-04": 1,
            "2017-08-04": 1,
            "2017-09-04": 5,
            "2017-10-04": 6,
            "2017-11-04": 10,
            "2017-12-04": 11,
            "2018-01-04": 12,
            "2018-02-04": 13,
            "2018-03-04": 15,
            "2018-04-04": 16,
            "2018-05-04": 17,
            "2018-06-04": 18,
            "2018-08-04": 21,
            "2018-11-04": 33,
            "2019-02-04": 44,
            "2019-08-15": 61,
            "2020-02-04": 79,
            "2020-08-04": 94,
            "2021-02-04": 120
        },
        "eprint_found": "2017-05-04",
        "id": "awan2017s",
        "paper_found": "2017-05-04",
        "title": "S-caffe: Co-designing mpi runtimes and caffe for scalable deep learning on modern gpu clusters",
        "url": "https://resource.hpisys.com/seminar-papers/2017/paper/20170427_PPoPP2017_S-Caffe%20Co-designing%20MPI%20Runtimes%20and%20Caffe%20for%20Scalable%20Deep%20Learning%20on%20Modern%20GPU%20Clusters.pdf"
    },
    "PPoPP_17_028": {
        "citedby": {
            "2017-05-04": 0,
            "2017-06-04": 0,
            "2017-07-04": 0,
            "2017-08-04": 0,
            "2017-09-04": 1,
            "2017-10-04": 1,
            "2017-11-04": 1,
            "2017-12-04": 1,
            "2018-01-04": 1,
            "2018-02-04": 1,
            "2018-03-04": 2,
            "2018-04-04": 3,
            "2018-05-04": 3,
            "2018-06-04": 3,
            "2018-08-04": 4,
            "2018-11-04": 4,
            "2019-02-04": 4,
            "2019-08-15": 9,
            "2020-02-04": 10,
            "2020-08-04": 13,
            "2021-02-04": 16
        },
        "eprint_found": "2017-05-04",
        "id": "shudler2017isoefficiency",
        "paper_found": "2017-05-04",
        "title": "Isoefficiency in practice: configuring and understanding the performance of task-based applications",
        "url": "https://dl.acm.org/doi/pdf/10.1145/3155284.3018770"
    },
    "PPoPP_17_029": {
        "citedby": {
            "2017-05-04": 0,
            "2017-06-04": 0,
            "2017-07-04": 0,
            "2017-08-04": 0,
            "2017-09-04": 0,
            "2017-10-04": 0,
            "2017-11-04": 0,
            "2017-12-04": 0,
            "2018-01-04": 0,
            "2018-02-04": 0,
            "2018-03-04": 0,
            "2018-04-04": 0,
            "2018-05-04": 0,
            "2018-06-04": 0,
            "2018-08-04": 1,
            "2018-11-04": 1,
            "2019-02-04": 3,
            "2019-08-15": 4,
            "2020-02-04": 4,
            "2020-08-04": 6,
            "2021-02-04": 8
        },
        "eprint_found": "2017-08-04",
        "id": "jiang2017grammar",
        "paper_found": "2017-05-04",
        "title": "Grammar-aware parallelization for scalable xpath querying",
        "url": "https://dl.acm.org/doi/pdf/10.1145/3155284.3018772"
    }
}