{
    "key": "SIGGRAPH_17",
    "conference": "International Conference on Computer Graphics and Interactive Techniques",
    "url": "http://s2017.siggraph.org/",
    "organization": [],
    "country": [],
    "postdate": [],
    "last_deadline": [],
    "review_days": [],
    "submissions": [],
    "min_reviews": [],
    "total_reviews": [],
    "double_blind": [],
    "rebuttal": [],
    "open_access": [],
    "age": [],
    "past_papers": [],
    "past_citations": [],
    "h5_index": [],
    "h5_median": [],
    "field": "Graphics",
    "subfield": [],
    "notes": [],
    "pc_chairs": [],
    "pc_members": [],
    "keynote_speakers": [],
    "session_chairs": [],
    "panelists": [],
    "papers": [
        {
            "key": "SIGGRAPH_17_001",
            "title": "CoLux: Multi-Object 3D Micro-Motion Analysis Using Speckle Imaging",
            "authors": [
                "BRANDON M. SMITH",
                "PRATHAM DESAI",
                "VISHAL AGARWAL",
                "MOHIT GUPTA (University of Wisconsin\u2013Madison)"
            ],
            "topics": []
        },
        {
            "key": "SIGGRAPH_17_002",
            "title": "VNect: Real-time 3D Human Pose Estimation with a Single RGB Camera",
            "authors": [
                "DUSHYANT MEHTA (Max Planck Institute for Informatics)",
                "SRINATH SRIDHAR (Max Planck Institute for Informatics)",
                "OLEKSANDR SOTNYCHENKO (Max Planck Institute for Informatics)",
                "HELGE RHODIN (Max Planck Institute for Informatics)",
                "MOHAMMAD SHAFIEI (Max Planck Institute for Informatics)",
                "HANS-PETER SEIDEL (Max Planck Institute for Informatics)",
                "WEIPENG XU (Max Planck Institute for Informatics)",
                "DAN CASAS (Universidad Rey Juan Carlos)",
                "CHRISTIAN THEOBALT (Max Planck Institute for Informatics)"
            ],
            "topics": []
        },
        {
            "key": "SIGGRAPH_17_003",
            "title": "Data-Driven Physics for Human Soft Tissue Animation",
            "authors": [
                "MEEKYOUNG KIM (Korea Advanced Institute of Science and Technology)",
                "GERARD PONS-MOLL (Max Planck Institute for Intelligent Systems)",
                "SERGI PUJADES (Max Planck Institute for Intelligent Systems)",
                "SEUNGBAE BANG (Korea Advanced Institute of Science and Technology)",
                "JINWOOK KIM (Korea Institute of Science and Technology)",
                "MICHAEL J. BLACK (Max Planck Institute for Intelligent Systems)",
                "SUNG-HEE LEE (Korea Advanced Institute of Science and Technology)"
            ],
            "topics": []
        },
        {
            "key": "SIGGRAPH_17_004",
            "title": "Learning Hierarchical Shape Segmentation and Labeling from Online Repositories",
            "authors": [
                "LI YI (Stanford University)",
                "LEONIDAS GUIBAS (Stanford University)",
                "AARON HERTZMANN (Adobe Research)",
                "VLADIMIR G. KIM (Adobe Research)",
                "HAO SU (Stanford University)",
                "ERSIN YUMER (Adobe Research)"
            ],
            "topics": []
        },
        {
            "key": "SIGGRAPH_17_005",
            "title": "Interactive Design of Animated Plushies",
            "authors": [
                "JAMES M. BERN (Carnegie Mellon University)",
                "KAI-HUNG CHANG (Carnegie Mellon University)",
                "STELIAN COROS (Carnegie Mellon University)"
            ],
            "topics": []
        },
        {
            "key": "SIGGRAPH_17_006",
            "title": "Focal Surface Displays",
            "authors": [
                "NATHAN MATSUDA (Oculus Research)",
                "ALEXANDER FIX (Oculus Research)",
                "DOUGLAS LANMAN (Oculus Research)"
            ],
            "topics": []
        },
        {
            "key": "SIGGRAPH_17_007",
            "title": "Accommodation and Comfort in Head-Mounted Displays",
            "authors": [
                "GEORGE-ALEX KOULIERIS (Inria, Universite\u0301 Co\u0302te d\u2019Azur)",
                "BEE BUI (University of California, Berkeley)",
                "MARTIN S. BANKS (University of California, Berkeley)",
                "GEORGE DRETTAKIS (Inria, Universite\u0301 Co\u0302te d\u2019Azur)"
            ],
            "topics": []
        },
        {
            "key": "SIGGRAPH_17_008",
            "title": "Infinite Continuous Adaptivity for Incompressible SPH",
            "authors": [
                "RENE WINCHENBACH (University of Siegen)",
                "HENDRIK HOCHSTETTER (University of Siegen)",
                "ANDREAS KOLB (University of Siegen)"
            ],
            "topics": []
        },
        {
            "key": "SIGGRAPH_17_009",
            "title": "A Forward Scattering Dipole Model from a Functional Integral Approximation",
            "authors": [
                "ROALD FREDERICKX",
                "PHILIP DUTRE\u0301 (KU Leuven)"
            ],
            "topics": []
        },
        {
            "key": "SIGGRAPH_17_010",
            "title": "DeepSketch2Face: A Deep Learning Based Sketching System for 3D Face and Caricature Modeling",
            "authors": [
                "XIAOGUANG HAN",
                "CHANG GAO",
                "YIZHOU YU (The University of Hong Kong)"
            ],
            "topics": []
        },
        {
            "key": "SIGGRAPH_17_011",
            "title": "Computational Video Editing for Dialogue-Driven Scenes",
            "authors": [
                "MACKENZIE LEAKE (Stanford University)",
                "ABE DAVIS (Stanford University)",
                "ANH TRUONG (Adobe Research)",
                "MANEESH AGRAWALA (Stanford University)"
            ],
            "topics": []
        },
        {
            "key": "SIGGRAPH_17_012",
            "title": "Time Slice Video Synthesis by Robust Video Alignment",
            "authors": [
                "ZHAOPENG CUI (Simon Fraser University)",
                "OLIVER WANG (Adobe Research)",
                "PING TAN (Simon Fraser University)",
                "JUE WANG (Adobe Research)"
            ],
            "topics": []
        },
        {
            "key": "SIGGRAPH_17_013",
            "title": "Hiding of Phase-Based Stereo Disparity for Ghost-Free Viewing Without Glasses",
            "authors": [
                "TAIKI FUKIAGE",
                "TAKAHIRO KAWABE",
                "SHIN\u2019YA NISHIDA (NTT Communication Science Laboratories)"
            ],
            "topics": []
        }
    ]
}
